feng_tools/__init__.py
feng_tools/ai/__init__.py
feng_tools/ai/client/__init__.py
feng_tools/ai/client/ollama_client.py
feng_tools/ai/client/openai_client.py
feng_tools/ai/image/__init__.py
feng_tools/ai/image/diffusers_tools.py
feng_tools/ai/model/__init__.py
feng_tools/ai/model/download_models_tools.py
feng_tools/ai/platform/__init__.py
feng_tools/ai/platform/huggingface_hub_tools.py
feng_tools/ai/platform/modelscope_tools.py
feng_tools/ai/prompt/__init__.py
feng_tools/ai/prompt/prompt_template_tools.py
feng_tools/ai/translation/__init__.py
feng_tools/ai/translation/translation_demo.py
feng_tools/app/__init__.py
feng_tools/app/base/__init__.py
feng_tools/app/base/AppPath.py
feng_tools/app/config/__init__.py
feng_tools/app/config/AppInfoSetting.py
feng_tools/app/config/AppPathSetting.py
feng_tools/app/config/DatabaseSetting.py
feng_tools/auth/__init__.py
feng_tools/auth/token/__init__.py
feng_tools/auth/token/memory_token_manager.py
feng_tools/auth/token/token_manager.py
feng_tools/auto/__init__.py
feng_tools/auto/app_auto/__init__.py
feng_tools/auto/app_auto/appium/__init__.py
feng_tools/auto/pc_auto/__init__.py
feng_tools/auto/task/__init__.py
feng_tools/auto/task/demo.py
feng_tools/auto/task/task_manager.py
feng_tools/auto/task/task_models.py
feng_tools/auto/web_auto/__init__.py
feng_tools/auto/web_auto/drission_page/__init__.py
feng_tools/auto/web_auto/drission_page/clone_site_tools.py
feng_tools/auto/web_auto/drission_page/drissionpage_auth_utils.py
feng_tools/auto/web_auto/playwright/__init__.py
feng_tools/auto/web_auto/selenium/__init__.py
feng_tools/base/__init__.py
feng_tools/base/convert/__init__.py
feng_tools/base/convert/type_convert_tools.py
feng_tools/base/datetime/__init__.py
feng_tools/base/datetime/datetime_tools.py
feng_tools/base/datetime/time_tools.py
feng_tools/base/datetime/week_tools.py
feng_tools/base/decorator/__init__.py
feng_tools/base/decorator/decorator_tools.py
feng_tools/base/email/__init__.py
feng_tools/base/encrypt/__init__.py
feng_tools-0.2.30.dist-info/LICENSE
feng_tools-0.2.30.dist-info/METADATA
feng_tools-0.2.30.dist-info/WHEEL
feng_tools-0.2.30.dist-info/RECORD
