Metadata-Version: 2.3
Name: feng-tools
Version: 0.2.30
Summary: 陈铁锋的Python工具包
License: MulanPSL2
Author: 编程Thinker
Author-email: imchentiefeng@aliyun.com
Requires-Python: >=3.10
Classifier: Programming Language :: Python :: 3
Classifier: Operating System :: OS Independent
Project-URL: Homepage, https://gitee.com/iron-source-galaxy/feng-tools
Project-URL: Issues, https://gitee.com/iron-source-galaxy/feng-tools/issues
